easy_release_automation/__init__.py
easy_release_automation/easy_release_automation.py
easy_release_automation/core/__init__.py
easy_release_automation/core/configuration.py
easy_release_automation/core/git_handler.py
easy_release_automation/core/plugin_executor.py
easy_release_automation/core/utils/__init__.py
easy_release_automation/core/utils/yaml_handler.py
easy_release_automation/interfaces/__init__.py
easy_release_automation/interfaces/modification_interface.py
easy_release_automation/interfaces/validation_interface.py
easy_release_automation/plugins/__init__.py
easy_release_automation/plugins/modification/__init__.py
easy_release_automation/plugins/modification/regex_replacer.py
easy_release_automation/plugins/modification/shell_modifier.py
easy_release_automation/plugins/modification/changelog/__init__.py
easy_release_automation/plugins/modification/changelog/changelog_unreleased_setter.py
easy_release_automation/plugins/modification/changelog/changelog_version_updater.py
easy_release_automation/plugins/modification/configuration_files/__init__.py
easy_release_automation/plugins/modification/configuration_files/raw_cfg_file_updater.py
easy_release_automation/plugins/modification/configuration_files/yaml_file_updater.py
easy_release_automation/plugins/modification/configuration_files/yaml_file_updater_v2.py
easy_release_automation/plugins/modification/python_requirements/requirements_updater.py
easy_release_automation/plugins/modification/python_requirements/requirements_updater_and_compiler.py
easy_release_automation/plugins/validation/__init__.py
easy_release_automation/plugins/validation/shell_validator.py
easy_release_automation/utils/__init__.py
easy_release_automation/utils/logging_wrapper.py
easy_release_automation-0.1.0.dist-info/LICENSE
easy_release_automation-0.1.0.dist-info/METADATA
easy_release_automation-0.1.0.dist-info/WHEEL
easy_release_automation-0.1.0.dist-info/entry_points.txt
easy_release_automation-0.1.0.dist-info/top_level.txt
easy_release_automation-0.1.0.dist-info/RECORD
