Metadata-Version: 2.1
Name: easy_release_automation
Version: 0.1.0
Summary: Easy-Release-Automation for Multi-Package-Versioning.
Author-email: Claus Seibold <claus.seibold@ingenics-digital.com>, David Kauschke <david.kauschke@ingenics-digital.com>, Martin Lautenbacher <martin.lautenbacher@ingenics-digital.com>
Project-URL: Homepage, https://github.com/IngenicsDigital/easy-release-automation
Project-URL: Issues, https://github.com/IngenicsDigital/easy-release-automation/issues
Keywords: EasyReleaseAutomation,git,AutomatedModification,AutomatedTesting
Classifier: Programming Language :: Python :: 3
Classifier: License :: OSI Approved :: MIT License
Classifier: Operating System :: OS Independent
Requires-Python: >=3.9
License-File: LICENSE
Requires-Dist: pip-tools >=7.4.1
Requires-Dist: pyyaml >=6.0
Requires-Dist: GitPython >=3.1.43
Requires-Dist: ruamel.yaml >=0.18.6
Requires-Dist: tomlkit >=0.12.5
Requires-Dist: pydantic >=2.7.1
Provides-Extra: test
Requires-Dist: black ==24.4.2 ; extra == 'test'
Requires-Dist: Flake8 ==3.8.0 ; extra == 'test'
Requires-Dist: flakehell ==0.9.0 ; extra == 'test'
Requires-Dist: mypy ==1.3.0 ; extra == 'test'
Requires-Dist: tox ==4.15.0 ; extra == 'test'
Requires-Dist: pytest ==7.1.2 ; extra == 'test'
Requires-Dist: pytest-cov ==2.12.1 ; extra == 'test'
Requires-Dist: pytest-html ==3.1.1 ; extra == 'test'
Requires-Dist: pytest-mock ==3.1.1 ; extra == 'test'
Requires-Dist: deepdiff ==7.0.1 ; extra == 'test'
Requires-Dist: license-header-check ==0.2.1 ; extra == 'test'
Requires-Dist: build ==1.2.1 ; extra == 'test'
